Metadata-Version: 1.0
Name: Julia-distributions
Version: 0.1
Summary: Gaussian and Binominal distributions
Home-page: UNKNOWN
Author: Julia
Author-email: UNKNOWN
License: UNKNOWN
Platform: UNKNOWN
